[
  {
    "list": [
      {
        "two": [
          "欣园123",
          "慧园"
        ],
        "point": [
          [
            114.00234,
            22.607893
          ],
          [
            114.002635,
            22.607665
          ],
          [
            114.003086,
            22.606967
          ],
          [
            114.003644,
            22.605694
          ],
          [
            114.003906,
            22.605372
          ],
          [
            114.003658,
            22.603711
          ],
          [
            114.003359,
            22.603087
          ]
        ]
      },
      {
        "two": [
          "慧园",
          "创园"
        ],
        "point": [
          [
            114.003359,
            22.603087
          ],
          [
            114.003066,
            22.603152
          ],
          [
            114.002738,
            22.603073
          ],
          [
            114.001766,
            22.603378
          ]
        ]
      },
      {
        "two": [
          "创园",
          "荔园"
        ],
        "point": [
          [
            114.001766,
            22.603378
          ],
          [
            114.001247,
            22.603622
          ],
          [
            114.000303,
            22.60385
          ],
          [
            114.000208,
            22.60349
          ]
        ]
      },
      {
        "two": [
          "荔园",
          "学生宿舍"
        ],
        "point": [
          [
            114.000208,
            22.60349
          ],
          [
            114.0002,
            22.603476
          ],
          [
            113.999717,
            22.603303
          ],
          [
            113.998644,
            22.602674
          ],
          [
            113.998494,
            22.602624
          ],
          [
            113.998735,
            22.602203
          ],
          [
            113.998811,
            22.601841
          ]
        ]
      },
      {
        "two": [
          "学生宿舍",
          "社康中心"
        ],
        "point": [
          [
            113.998811,
            22.601841
          ],
          [
            113.998922,
            22.60165
          ],
          [
            113.999217,
            22.601333
          ],
          [
            113.999421,
            22.60118
          ],
          [
            113.999997,
            22.600589
          ],
          [
            114.000395,
            22.600139
          ],
          [
            114.00061,
            22.600051
          ],
          [
            114.000923,
            22.600002
          ]
        ]
      },
      {
        "two": [
          "社康中心",
          "教工餐厅"
        ],
        "point": [
          [
            114.000923,
            22.600002
          ],
          [
            114.001806,
            22.600047
          ],
          [
            114.002718,
            22.600339
          ],
          [
            114.002851,
            22.600392
          ]
        ]
      },
      {
        "two": [
          "教工餐厅",
          "专家公寓"
        ],
        "point": [
          [
            114.002851,
            22.600392
          ],
          [
            114.003011,
            22.60025
          ],
          [
            114.003145,
            22.599565
          ],
          [
            114.003332,
            22.599145
          ],
          [
            114.00344,
            22.598968
          ]
        ]
      },
      {
        "two": [
          "专家公寓",
          "3号门"
        ],
        "point": [
          [
            114.00344,
            22.598968
          ],
          [
            114.003626,
            22.598773
          ],
          [
            114.003826,
            22.598447
          ],
          [
            114.00383,
            22.598041
          ],
          [
            114.004014,
            22.597725
          ],
          [
            114.004126,
            22.5976
          ],
          [
            114.003717,
            22.597437
          ]
        ]
      },
      {
        "two": [
          "3号门",
          "2号门"
        ],
        "point": [
          [
            114.003717,
            22.597437
          ],
          [
            114.003332,
            22.597316
          ],
          [
            114.003041,
            22.597193
          ],
          [
            114.002759,
            22.596981
          ],
          [
            114.002448,
            22.596411
          ],
          [
            114.002109,
            22.596013
          ],
          [
            114.001671,
            22.595657
          ],
          [
            114.001119,
            22.595125
          ]
        ]
      },
      {
        "two": [
          "2号门",
          "1号门"
        ],
        "point": [
          [
            114.001119,
            22.595125
          ],
          [
            114.000336,
            22.594268
          ],
          [
            114.000073,
            22.593619
          ],
          [
            113.999596,
            22.593243
          ],
          [
            113.998768,
            22.593133
          ]
        ]
      },
      {
        "two": [
          "1号门",
          "行政楼"
        ],
        "point": [
          [
            113.998768,
            22.593133
          ],
          [
            113.998249,
            22.593372
          ],
          [
            113.997467,
            22.594094
          ]
        ]
      },
      {
        "two": [
          "行政楼",
          "7号门"
        ],
        "point": [
          [
            113.997467,
            22.594094
          ],
          [
            113.997202,
            22.594287
          ],
          [
            113.996778,
            22.594351
          ],
          [
            113.995759,
            22.594103
          ],
          [
            113.995345,
            22.594232
          ]
        ]
      },
      {
        "two": [
          "7号门",
          "科研楼"
        ],
        "point": [
          [
            113.995345,
            22.594232
          ],
          [
            113.995297,
            22.594474
          ],
          [
            113.995399,
            22.595856
          ],
          [
            113.995635,
            22.596223
          ],
          [
            113.996171,
            22.596446
          ],
          [
            113.996604,
            22.596742
          ]
        ]
      },
      {
        "two": [
          "科研楼",
          "工学院"
        ],
        "point": [
          [
            113.996604,
            22.596742
          ],
          [
            113.996784,
            22.596924
          ],
          [
            113.996972,
            22.597275
          ],
          [
            113.99709,
            22.597751
          ],
          [
            113.997008,
            22.598137
          ],
          [
            113.996799,
            22.598464
          ],
          [
            113.996557,
            22.598702
          ],
          [
            113.995468,
            22.599618
          ],
          [
            113.99534,
            22.59995
          ],
          [
            113.995249,
            22.600505
          ]
        ]
      }
    ],
    "name": "busline1"
  },
  {
    "list": [
      {
        "two": [
          "欣园",
          "慧园"
        ],
        "point": [
          [
            114.00234,
            22.607893
          ],
          [
            114.002635,
            22.607665
          ],
          [
            114.003086,
            22.606967
          ],
          [
            114.003644,
            22.605694
          ],
          [
            114.003906,
            22.605372
          ],
          [
            114.003658,
            22.603711
          ],
          [
            114.003359,
            22.603087
          ]
        ]
      },
      {
        "two": [
          "慧园",
          "创园"
        ],
        "point": [
          [
            114.003359,
            22.603087
          ],
          [
            114.003066,
            22.603152
          ],
          [
            114.002738,
            22.603073
          ],
          [
            114.001766,
            22.603378
          ]
        ]
      },
      {
        "two": [
          "创园",
          "荔园"
        ],
        "point": [
          [
            114.001766,
            22.603378
          ],
          [
            114.001247,
            22.603622
          ],
          [
            114.000303,
            22.60385
          ],
          [
            114.000208,
            22.60349
          ]
        ]
      },
      {
        "two": [
          "荔园",
          "学生宿舍"
        ],
        "point": [
          [
            114.000208,
            22.60349
          ],
          [
            114.0002,
            22.603476
          ],
          [
            113.999717,
            22.603303
          ],
          [
            113.998644,
            22.602674
          ],
          [
            113.998494,
            22.602624
          ],
          [
            113.998735,
            22.602203
          ],
          [
            113.998811,
            22.601841
          ]
        ]
      },
      {
        "two": [
          "学生宿舍",
          "科研楼"
        ],
        "point": [
          [
            113.998811,
            22.601841
          ],
          [
            113.99892,
            22.601665
          ],
          [
            113.99922,
            22.601348
          ],
          [
            113.999129,
            22.601116
          ],
          [
            113.998931,
            22.600764
          ],
          [
            113.998019,
            22.60062
          ],
          [
            113.997826,
            22.600393
          ],
          [
            113.997686,
            22.600289
          ],
          [
            113.997472,
            22.60018
          ],
          [
            113.997246,
            22.599962
          ],
          [
            113.99701,
            22.599714
          ],
          [
            113.996769,
            22.599174
          ],
          [
            113.996549,
            22.598674
          ],
          [
            113.99679,
            22.598456
          ],
          [
            113.99701,
            22.598154
          ],
          [
            113.997075,
            22.597758
          ],
          [
            113.996983,
            22.597258
          ],
          [
            113.996774,
            22.596951
          ],
          [
            113.996604,
            22.596742
          ]
        ]
      }
    ],
    "name": "busline2"
  }
]